collective.contentalerts-4.0.0-py3.8-nspkg.pth
collective/contentalerts/__init__.py
collective/contentalerts/configure.zcml
collective/contentalerts/contentrules.py
collective/contentalerts/contentrules.zcml
collective/contentalerts/handlers.py
collective/contentalerts/handlers.zcml
collective/contentalerts/interfaces.py
collective/contentalerts/permissions.zcml
collective/contentalerts/testing.py
collective/contentalerts/utilities.py
collective/contentalerts/browser/__init__.py
collective/contentalerts/browser/configure.zcml
collective/contentalerts/browser/controlpanel.py
collective/contentalerts/browser/discard_alert.py
collective/contentalerts/browser/review_objects.py
collective/contentalerts/browser/static/.gitkeep
collective/contentalerts/locales/update.sh
collective/contentalerts/locales/de/LC_MESSAGES/collective.contentalerts.po
collective/contentalerts/profiles/default/browserlayer.xml
collective/contentalerts/profiles/default/controlpanel.xml
collective/contentalerts/profiles/default/metadata.xml
collective/contentalerts/profiles/default/registry.xml
collective/contentalerts/profiles/default/rolemap.xml
collective/contentalerts/profiles/uninstall/browserlayer.xml
collective/contentalerts/profiles/uninstall/controlpanel.xml
collective/contentalerts/profiles/uninstall/metadata.xml
collective/contentalerts/profiles/uninstall/registry.xml
collective/contentalerts/tests/__init__.py
collective/contentalerts/tests/functional_contentrules.rst
collective/contentalerts/tests/test_contentrules.py
collective/contentalerts/tests/test_doctests.py
collective/contentalerts/tests/test_genericsetup.py
collective/contentalerts/tests/test_handlers.py
collective/contentalerts/tests/test_setup.py
collective/contentalerts/tests/test_utilities.py
collective/contentalerts/tests/test_views.py
collective.contentalerts-4.0.0.dist-info/METADATA
collective.contentalerts-4.0.0.dist-info/WHEEL
collective.contentalerts-4.0.0.dist-info/entry_points.txt
collective.contentalerts-4.0.0.dist-info/namespace_packages.txt
collective.contentalerts-4.0.0.dist-info/top_level.txt
collective.contentalerts-4.0.0.dist-info/RECORD
