Metadata-Version: 2.1
Name: collective.contentalerts
Version: 4.0.0
Summary: An add-on for Plone to get alerts about content
Home-page: https://github.com/collective/collective.contentalerts
Author: Gil Forcada
Author-email: gilforcada@gmail.com
License: GPL version 2
Keywords: Python Plone
Classifier: Development Status :: 5 - Production/Stable
Classifier: Environment :: Web Environment
Classifier: Framework :: Plone
Classifier: Framework :: Plone :: 6.0
Classifier: Framework :: Plone :: Addon
Classifier: Programming Language :: Python
Classifier: Programming Language :: Python :: 3
Classifier: Programming Language :: Python :: 3.8
Classifier: Programming Language :: Python :: 3.9
Classifier: Programming Language :: Python :: 3.10
Classifier: Programming Language :: Python :: 3.11
Classifier: Operating System :: OS Independent
Classifier: License :: OSI Approved :: GNU General Public License v2 (GPLv2)
Requires-Python: >=3.8
Requires-Dist: plone.api >=1.4.11
Requires-Dist: plone.app.contentrules
Requires-Dist: plone.app.contenttypes
Requires-Dist: plone.app.discussion
Requires-Dist: plone.app.registry
Requires-Dist: plone.app.textfield
Requires-Dist: plone.app.z3cform
Requires-Dist: plone.contentrules
Requires-Dist: plone.registry
Requires-Dist: plone.stringinterp
Requires-Dist: Products.CMFCore
Requires-Dist: Products.CMFPlone
Requires-Dist: Products.GenericSetup
Requires-Dist: setuptools
Requires-Dist: z3c.form
Requires-Dist: Zope
Requires-Dist: zope.component
Requires-Dist: zope.i18nmessageid
Requires-Dist: zope.interface
Requires-Dist: zope.publisher
Requires-Dist: zope.schema
Provides-Extra: async
Requires-Dist: collective.taskqueue ; extra == 'async'
Provides-Extra: test
Requires-Dist: Acquisition ; extra == 'test'
Requires-Dist: plone.app.discussion ; extra == 'test'
Requires-Dist: plone.app.testing ; extra == 'test'
Requires-Dist: plone.browserlayer ; extra == 'test'
Requires-Dist: plone.registry ; extra == 'test'
Requires-Dist: plone.testing ; extra == 'test'
Requires-Dist: Products.CMFPlone ; extra == 'test'
Requires-Dist: Products.MailHost ; extra == 'test'
Requires-Dist: Products.statusmessages ; extra == 'test'
Requires-Dist: transaction ; extra == 'test'
